mp_face_stylizer/main.py
mp_face_stylizer/sdk.py
mp_face_stylizer-0.0.2.dist-info/METADATA
mp_face_stylizer-0.0.2.dist-info/WHEEL
mp_face_stylizer-0.0.2.dist-info/entry_points.txt
mp_face_stylizer-0.0.2.dist-info/licenses/LICENSE
mp_face_stylizer-0.0.2.dist-info/RECORD
